robo_gym_server_modules/__init__.py
robo_gym_server_modules/robot_server/__init__.py
robo_gym_server_modules/robot_server/client.py
robo_gym_server_modules/robot_server/grpc_msgs/__init__.py
robo_gym_server_modules/robot_server/grpc_msgs/python/__init__.py
robo_gym_server_modules/robot_server/grpc_msgs/python/robot_server_pb2.py
robo_gym_server_modules/robot_server/grpc_msgs/python/robot_server_pb2_grpc.py
robo_gym_server_modules/server_manager/__init__.py
robo_gym_server_modules/server_manager/client.py
robo_gym_server_modules/server_manager/server.py
robo_gym_server_modules/server_manager/grpc_msgs/__init__.py
robo_gym_server_modules/server_manager/grpc_msgs/python3/__init__.py
robo_gym_server_modules/server_manager/grpc_msgs/python3/server_manager_pb2.py
robo_gym_server_modules/server_manager/grpc_msgs/python3/server_manager_pb2_grpc.py
robo_gym_server_modules-0.1.1.data/scripts/attach-to-server-manager
robo_gym_server_modules-0.1.1.data/scripts/kill-all-robot-servers
robo_gym_server_modules-0.1.1.data/scripts/kill-server-manager
robo_gym_server_modules-0.1.1.data/scripts/start-server-manager
robo_gym_server_modules-0.1.1.dist-info/LICENSE
robo_gym_server_modules-0.1.1.dist-info/METADATA
robo_gym_server_modules-0.1.1.dist-info/WHEEL
robo_gym_server_modules-0.1.1.dist-info/top_level.txt
robo_gym_server_modules-0.1.1.dist-info/RECORD
